chempp/__init__.py
chempp/interpreter.py
chempp/safe_api.py
chempp/version.py
chempp-0.1.4.dist-info/licenses/LICENSE.txt
chempp-0.1.4.dist-info/METADATA
chempp-0.1.4.dist-info/WHEEL
chempp-0.1.4.dist-info/top_level.txt
chempp-0.1.4.dist-info/RECORD
