Metadata-Version: 2.4
Name: chempp
Version: 0.1.4
Summary: Chem++ for Chemical System Programming
Author-email: Prakritee Chakraborty <kriti.guitar@gmail.com>
License: MIT
Requires-Python: >=3.7
License-File: LICENSE.txt
Requires-Dist: requests
Requires-Dist: aiohttp
Dynamic: license-file
